MANIFEST.in
README.md
setup.py
iglobal/__init__.py
iglobal/api.py
iglobal/exceptions.py
python_iglobal.egg-info/PKG-INFO
python_iglobal.egg-info/SOURCES.txt
python_iglobal.egg-info/dependency_links.txt
python_iglobal.egg-info/not-zip-safe
python_iglobal.egg-info/requires.txt
python_iglobal.egg-info/top_level.txt