Metadata-Version: 1.1
Name: python-iglobal
Version: 0.1
Summary: Python wrapper for the iGlobalStores.com REST API.
Home-page: https://github.com/RidleyLarsen/python-iglobal
Author: Ridley Larsen
Author-email: ridley@iglobalstores.com
License: UNKNOWN
Keywords: iglobal api
Platform: UNKNOWN
Classifier: Intended Audience :: Developers
Classifier: Programming Language :: Python
Classifier: Programming Language :: Python :: 2
Classifier: Programming Language :: Python :: 2.7
Classifier: Programming Language :: Python :: 3
Classifier: Programming Language :: Python :: 3.2
Classifier: Programming Language :: Python :: 3.3
Classifier: Programming Language :: Python :: 3.4
Classifier: Development Status :: 4 - Beta
Classifier: Operating System :: OS Independent
